openNucleome/.gitignore
openNucleome/README.md
openNucleome/__init__.py
openNucleome/chromosome.py
openNucleome/lamina.py
openNucleome/nucleolus.py
openNucleome/speckle.py
openNucleome/whole_nucleus_model.py
openNucleome/parameters/HFF_100KB/chr_lam_param.txt
openNucleome/parameters/HFF_100KB/chr_nuc_param.txt
openNucleome/parameters/HFF_100KB/chr_spec_param.txt
openNucleome/parameters/HFF_100KB/chromatin_info.txt
openNucleome/parameters/HFF_100KB/compt_param_file.txt
openNucleome/parameters/HFF_100KB/ideal_param_file.txt
openNucleome/parameters/HFF_100KB/interchr_param_file.txt
openNucleome/utils/DamID_TSASeq_calculation.py
openNucleome/utils/__init__.py
openNucleome/utils/chromosome_contact_calculation.f90
openNucleome/utils/coor_transformation.py
openNucleome/utils/final_frame.py
openNucleome/utils/__pycache__/DamID_TSASeq_calculation.cpython-36.pyc
openNucleome-1.3.0.dist-info/LICENSE
openNucleome-1.3.0.dist-info/METADATA
openNucleome-1.3.0.dist-info/WHEEL
openNucleome-1.3.0.dist-info/top_level.txt
openNucleome-1.3.0.dist-info/RECORD
