Metadata-Version: 2.1
Name: openNucleome
Version: 1.3.0
Project-URL: Homepage, https://github.com/ZhangGroup-MITChemistry/OpenNucleome
Classifier: Programming Language :: Python :: 3
Classifier: License :: OSI Approved :: MIT License
Classifier: Operating System :: OS Independent
Requires-Python: >=3.6
License-File: LICENSE
Requires-Dist: numpy
Requires-Dist: pandas
Requires-Dist: scipy
Requires-Dist: scikit-learn
Requires-Dist: mdtraj
Requires-Dist: MDAnalysis
Requires-Dist: OpenMM
